{
  "fetched_at": "16:20:04",
  "as_of": "2026-06-16 16:20",
  "available": true,
  "spots": [
    {
      "ticker": "SPY",
      "price": 753.35,
      "change_pct": -0.2,
      "last_tick": "EOD"
    },
    {
      "ticker": "QQQ",
      "price": 735.52,
      "change_pct": -1.14,
      "last_tick": "EOD"
    },
    {
      "ticker": "IWM",
      "price": 293.87,
      "change_pct": -0.26,
      "last_tick": "EOD"
    },
    {
      "ticker": "VIXY",
      "price": 21.64,
      "change_pct": -0.3,
      "last_tick": "EOD"
    }
  ],
  "pcr_live": [
    {
      "ticker": "SPY",
      "pcr": 0.0,
      "tag": "CALL-HEAVY",
      "color": "green",
      "n_contracts": 250
    },
    {
      "ticker": "QQQ",
      "pcr": 0.02,
      "tag": "CALL-HEAVY",
      "color": "green",
      "n_contracts": 250
    }
  ]
}