{
  "fetched_at": "15:05:04",
  "as_of": "2026-07-23 15:05",
  "available": true,
  "spots": [
    {
      "ticker": "SPY",
      "price": 738.79,
      "change_pct": -1.15,
      "last_tick": "EOD"
    },
    {
      "ticker": "QQQ",
      "price": 692.55,
      "change_pct": -1.81,
      "last_tick": "EOD"
    },
    {
      "ticker": "IWM",
      "price": 292.13,
      "change_pct": -0.57,
      "last_tick": "EOD"
    },
    {
      "ticker": "VIXY",
      "price": 21.95,
      "change_pct": 5.91,
      "last_tick": "EOD"
    }
  ],
  "pcr_live": [
    {
      "ticker": "SPY",
      "pcr": 1.0,
      "tag": "BALANCED",
      "color": "amber-soft",
      "n_contracts": 250
    },
    {
      "ticker": "QQQ",
      "pcr": 0.02,
      "tag": "CALL-HEAVY",
      "color": "green",
      "n_contracts": 250
    }
  ]
}