{
  "fetched_at": "18:15:04",
  "as_of": "2026-06-15 18:15",
  "available": true,
  "spots": [
    {
      "ticker": "SPY",
      "price": 755.23,
      "change_pct": 1.82,
      "last_tick": "EOD"
    },
    {
      "ticker": "QQQ",
      "price": 743.45,
      "change_pct": 3.06,
      "last_tick": "EOD"
    },
    {
      "ticker": "IWM",
      "price": 295.22,
      "change_pct": 0.77,
      "last_tick": "EOD"
    },
    {
      "ticker": "VIXY",
      "price": 21.94,
      "change_pct": -5.8,
      "last_tick": "EOD"
    }
  ],
  "pcr_live": [
    {
      "ticker": "SPY",
      "pcr": 0.0,
      "tag": "CALL-HEAVY",
      "color": "green",
      "n_contracts": 250
    },
    {
      "ticker": "QQQ",
      "pcr": 0.02,
      "tag": "CALL-HEAVY",
      "color": "green",
      "n_contracts": 250
    }
  ]
}