{
  "fetched_at": "18:35:03",
  "as_of": "2026-07-15 18:35",
  "available": true,
  "spots": [
    {
      "ticker": "SPY",
      "price": 754.33,
      "change_pct": 0.33,
      "last_tick": "EOD"
    },
    {
      "ticker": "QQQ",
      "price": 717.69,
      "change_pct": -0.28,
      "last_tick": "EOD"
    },
    {
      "ticker": "IWM",
      "price": 295.74,
      "change_pct": 0.42,
      "last_tick": "EOD"
    },
    {
      "ticker": "VIXY",
      "price": 20.14,
      "change_pct": -2.49,
      "last_tick": "EOD"
    }
  ],
  "pcr_live": [
    {
      "ticker": "SPY",
      "pcr": 0.03,
      "tag": "CALL-HEAVY",
      "color": "green",
      "n_contracts": 250
    },
    {
      "ticker": "QQQ",
      "pcr": 0.06,
      "tag": "CALL-HEAVY",
      "color": "green",
      "n_contracts": 250
    }
  ]
}